{"frames": {

"CachedBmp_182":
{
	"frame": {"x":0,"y":1616,"w":1144,"h":200},
	"rotated": false,
	"trimmed": false,
	"spriteSourceSize": {"x":0,"y":0,"w":1144,"h":200},
	"sourceSize": {"w":1144,"h":200}
},
"CachedBmp_183":
{
	"frame": {"x":0,"y":1414,"w":1144,"h":200},
	"rotated": false,
	"trimmed": false,
	"spriteSourceSize": {"x":0,"y":0,"w":1144,"h":200},
	"sourceSize": {"w":1144,"h":200}
},
"CachedBmp_184":
{
	"frame": {"x":0,"y":1212,"w":1144,"h":200},
	"rotated": false,
	"trimmed": false,
	"spriteSourceSize": {"x":0,"y":0,"w":1144,"h":200},
	"sourceSize": {"w":1144,"h":200}
},
"CachedBmp_185":
{
	"frame": {"x":0,"y":1010,"w":1144,"h":200},
	"rotated": false,
	"trimmed": false,
	"spriteSourceSize": {"x":0,"y":0,"w":1144,"h":200},
	"sourceSize": {"w":1144,"h":200}
},
"CachedBmp_186":
{
	"frame": {"x":0,"y":808,"w":1144,"h":200},
	"rotated": false,
	"trimmed": false,
	"spriteSourceSize": {"x":0,"y":0,"w":1144,"h":200},
	"sourceSize": {"w":1144,"h":200}
},
"CachedBmp_187":
{
	"frame": {"x":0,"y":606,"w":1190,"h":200},
	"rotated": false,
	"trimmed": false,
	"spriteSourceSize": {"x":0,"y":0,"w":1190,"h":200},
	"sourceSize": {"w":1190,"h":200}
},
"CachedBmp_188":
{
	"frame": {"x":0,"y":404,"w":1190,"h":200},
	"rotated": false,
	"trimmed": false,
	"spriteSourceSize": {"x":0,"y":0,"w":1190,"h":200},
	"sourceSize": {"w":1190,"h":200}
},
"CachedBmp_189":
{
	"frame": {"x":0,"y":202,"w":1190,"h":200},
	"rotated": false,
	"trimmed": false,
	"spriteSourceSize": {"x":0,"y":0,"w":1190,"h":200},
	"sourceSize": {"w":1190,"h":200}
},
"CachedBmp_190":
{
	"frame": {"x":0,"y":0,"w":1190,"h":200},
	"rotated": false,
	"trimmed": false,
	"spriteSourceSize": {"x":0,"y":0,"w":1190,"h":200},
	"sourceSize": {"w":1190,"h":200}
},
"CachedBmp_212":
{
	"frame": {"x":0,"y":1818,"w":1959,"h":113},
	"rotated": false,
	"trimmed": false,
	"spriteSourceSize": {"x":0,"y":0,"w":1959,"h":113},
	"sourceSize": {"w":1959,"h":113}
}},
"meta": {
	"app": "Adobe Animate",
	"version": "23.0.2.103",
	"image": "index copy_atlas_8.png",
	"format": "undefined",
	"size": {"w":2048,"h":2048},
	"scale": "1"
}
}
